opadk/__init__.py
opadk/models.py
opadk/opa.py
opadk/plugin.py
opadk/py.typed
opadk-0.1.1.dist-info/WHEEL
opadk-0.1.1.dist-info/METADATA
opadk-0.1.1.dist-info/RECORD
