Metadata-Version: 2.3
Name: opadk
Version: 0.1.1
Summary: Plugin for Agent Development Kit (ADK) that integrates with Open Policy Agent (OPA) to enforce policies on agents and tools.
Author: becojo
Author-email: becojo <opadk@ezoidc.dev>
Requires-Dist: aiohttp>=3.13.2
Requires-Dist: google-adk>=1.19.0
Requires-Dist: pydantic>=2.12.5
Requires-Python: >=3.13
Project-URL: Homepage, https://github.com/ezoidc/opadk
Project-URL: Issues, https://github.com/ezoidc/opadk/issues
